fmbench/0_setup.ipynb
fmbench/1_generate_data.ipynb
fmbench/2_deploy_model.ipynb
fmbench/3_run_inference.ipynb
fmbench/4_get_evaluations.ipynb
fmbench/5_model_metric_analysis.ipynb
fmbench/6_cleanup.ipynb
fmbench/__init__.py
fmbench/bring_your_own_dataset.ipynb
fmbench/config_filepath.txt
fmbench/defaults.py
fmbench/globals.py
fmbench/main.py
fmbench/requirements.txt
fmbench/utils.py
fmbench/configs/model_eval_all_info.yml
fmbench/configs/pricing.yml
fmbench/configs/pricing_fallback.yml
fmbench/configs/NousResearchHermes70B/config-Nous-Hermes3-1-70b-g5.48xl-tp-8-mc-max-djl.yml
fmbench/configs/NousResearchHermes70B/config-Nous-Hermes3-1-70b-inf2.48xl-triton-tp24.yml
fmbench/configs/NousResearchHermes70B/config-Nous-Hermes3-1-70b-trn1.32xl-deploy-ec2-triton.yml
fmbench/configs/bedrock/config-bedrock-all-anthropic-models-longbench-data.yml
fmbench/configs/bedrock/config-bedrock-anthropic-models-OpenOrca.yml
fmbench/configs/bedrock/config-bedrock-claude.yml
fmbench/configs/bedrock/config-bedrock-evals-only-conc-1.yml
fmbench/configs/bedrock/config-bedrock-haiku-sonnet-majority-voting.yml
fmbench/configs/bedrock/config-bedrock-llama3-1-70b-streaming.yml
fmbench/configs/bedrock/config-bedrock-llama3-1-8b-streaming.yml
fmbench/configs/bedrock/config-bedrock-llama3-1-no-streaming.yml
fmbench/configs/bedrock/config-bedrock-llama3-1.yml
fmbench/configs/bedrock/config-bedrock-llama3-streaming.yml
fmbench/configs/bedrock/config-bedrock-models-OpenOrca.yml
fmbench/configs/bedrock/config-bedrock-titan-text-express.yml
fmbench/configs/bedrock/config-bedrock.yml
fmbench/configs/bedrock/config-claude-3-5-sonnet-v2.yml
fmbench/configs/bedrock/config-claude-dolly-dataset.yml
fmbench/configs/bedrock/config-llama-3-2-11b-databricks-dolly-15k.yml
fmbench/configs/bedrock/config-llama-3-2-1b-3b-no-evals.yml
fmbench/configs/bedrock/config-llama-3-2-1b-3b.yml
fmbench/configs/bedrock/config-llama-3-2-all-models-longbench-hf-version.yml
fmbench/configs/bedrock/config-llama-3-2-all-models.yml
fmbench-2.1.6.dist-info/licenses/LICENSE
fmbench-2.1.6.dist-info/METADATA
fmbench-2.1.6.dist-info/WHEEL
fmbench-2.1.6.dist-info/entry_points.txt
fmbench-2.1.6.dist-info/top_level.txt
fmbench-2.1.6.dist-info/RECORD
