Metadata-Version: 2.4
Name: fmbench
Version: 2.1.6
Summary: Benchmark performance of **any Foundation Model (FM)** deployed on **any AWS Generative AI service**, be it **Amazon SageMaker**, **Amazon Bedrock**, **Amazon EKS**, or **Amazon EC2**. The FMs could be deployed on these platforms either directly through `FMbench`, or, if they are already deployed then also they could be benchmarked through the **Bring your own endpoint** mode supported by `FMBench`.
Author-email: Amit Arora <aroraai@amazon.com>, Madhur Prashant <Madhurpt@amazon.com>
License: MIT
Keywords: benchmarking,sagemaker,bedrock,bring your own endpoint,generative-ai,foundation-models,llama3,ec2,eks
Classifier: Programming Language :: Python :: 3
Classifier: License :: OSI Approved :: MIT License
Classifier: Operating System :: OS Independent
Requires-Python: <3.13,>=3.12
License-File: LICENSE
Requires-Dist: boto3>=1.36.6
Requires-Dist: datasets>=3.2.0
Requires-Dist: ec2-metadata>=2.14.0
Requires-Dist: ipykernel>=6.29.5
Requires-Dist: ipywidgets>=8.1.5
Requires-Dist: jinja2>=3.1.5
Requires-Dist: jupyter>=1.1.1
Requires-Dist: jupyter-client>=8.6.3
Requires-Dist: kaleido==0.2.1
Requires-Dist: litellm>=1.59.8
Requires-Dist: mkdocs>=1.6.1
Requires-Dist: mkdocs-material>=9.5.50
Requires-Dist: mknotebooks>=0.8.0
Requires-Dist: nvitop>=1.4.1
Requires-Dist: pandas>=2.2.3
Requires-Dist: papermill>=2.6.0
Requires-Dist: pip>=24.3.1
Requires-Dist: plotly>=5.24.1
Requires-Dist: psutil>=6.1.1
Requires-Dist: pydantic>=2.10.6
Requires-Dist: pyyaml>=6.0.2
Requires-Dist: ray>=2.41.0
Requires-Dist: requests>=2.32.3
Requires-Dist: sagemaker>=2.237.3
Requires-Dist: seaborn>=0.13.2
Requires-Dist: sentence-transformers>=3.4.0
Requires-Dist: tomark>=0.1.4
Requires-Dist: torch>=2.5.1
Requires-Dist: tqdm>=4.67.1
Requires-Dist: transformers>=4.48.1
Requires-Dist: twine>=6.1.0
Requires-Dist: typing-extensions>=4.12.2
Requires-Dist: zmq>=0.0.0
Dynamic: license-file
